save_monger-0.4.0.dist-info/top_level.txt
save_monger-0.4.0.dist-info/WHEEL
save_monger-0.4.0.dist-info/LICENSE
save_monger-0.4.0.dist-info/METADATA
save_monger-0.4.0.dist-info/RECORD
save_monger/nim_save_monger.pyi
save_monger/tc_save.py
save_monger/nim_save_monger.cpython-310-i386-linux-gnu.so
save_monger/__init__.py
save_monger/models.py
