Metadata-Version: 2.1
Name: save-monger
Version: 0.4.0
License-File: LICENSE
Requires-Dist: pydantic
